fastapi_cap-0.2.0.dist-info/licenses/LICENSE
fastapicap/__init__.py
fastapicap/base_limiter.py
fastapicap/connection.py
fastapicap/lua.py
fastapicap/middleware.py
fastapicap/strategy/__init__.py
fastapicap/strategy/fixed_window.py
fastapicap/strategy/gcra.py
fastapicap/strategy/leaky_bucket.py
fastapicap/strategy/sliding_window.py
fastapicap/strategy/sliding_window_log.py
fastapicap/strategy/token_bucket.py
fastapi_cap-0.2.0.dist-info/METADATA
fastapi_cap-0.2.0.dist-info/WHEEL
fastapi_cap-0.2.0.dist-info/top_level.txt
fastapi_cap-0.2.0.dist-info/RECORD
