Metadata-Version: 2.4
Name: fastapi-cap
Version: 0.2.0
Summary: A robust, extensible, and production-ready rate limiting library for FastAPI, supporting multiple algorithms and Redis backend.
Author-email: Bijay Nayak <bijay6779@gmail.com>
License-Expression: MIT
Project-URL: Homepage, https://github.com/devbijay/FastAPI-Cap
Project-URL: Documentation, https://devbijay.github.io/FastAPI-Cap/
Project-URL: Repository, https://github.com/devbijay/FastAPI-Cap.git
Project-URL: Issues, https://github.com/devbijay/FastAPI-Cap/issues
Keywords: fastapi,rate-limiter,redis,api,throttling,limiter,web,asgi
Classifier: Development Status :: 4 - Beta
Classifier: Intended Audience :: Developers
Classifier: Programming Language :: Python :: 3.9
Classifier: Programming Language :: Python :: 3.10
Classifier: Programming Language :: Python :: 3.11
Classifier: Programming Language :: Python :: 3.12
Classifier: Programming Language :: Python :: 3.13
Classifier: Framework :: FastAPI
Classifier: Topic :: Software Development :: Libraries
Classifier: Topic :: Internet :: WWW/HTTP
Classifier: Operating System :: OS Independent
Requires-Python: >=3.9
License-File: LICENSE
Requires-Dist: fastapi>=0.95.0
Requires-Dist: redis>=4.2.0
Dynamic: license-file
